cve_lookup/__init__.py
cve_lookup/__main__.py
cve_lookup/cve.py
cve_lookup/vector/__init__.py
cve_lookup/vector/cvss2.py
cve_lookup/vector/cvss3.py
cve_lookup/vector/exceptions.py
cve_lookup/vector/tools.py
cve_lookup-0.2.0.dist-info/LICENSE.md
cve_lookup-0.2.0.dist-info/METADATA
cve_lookup-0.2.0.dist-info/WHEEL
cve_lookup-0.2.0.dist-info/entry_points.txt
cve_lookup-0.2.0.dist-info/top_level.txt
cve_lookup-0.2.0.dist-info/RECORD
