Metadata-Version: 2.1
Name: cve-lookup
Version: 0.2.0
Summary: Look up CVEs and get details about them.
Home-page: UNKNOWN
Author: MachineThing
License: MIT
Project-URL: Repository, https://github.com/machinething/cve_lookup
Project-URL: Issues, https://github.com/machinething/cve_lookup/issues
Project-URL: MachineThing, https://masonfisher.net
Keywords: cve,simple,requests,search,cvss
Platform: UNKNOWN
Classifier: Operating System :: OS Independent
Classifier: License :: OSI Approved :: MIT License
Classifier: Intended Audience :: Developers
Classifier: Programming Language :: Python :: 3.8
Classifier: Programming Language :: Python :: 3.9
Classifier: Programming Language :: Python :: 3 :: Only
Requires-Python: >3.8,<4
License-File: LICENSE.md
Requires-Dist: beautifulsoup4
Requires-Dist: requests
Requires-Dist: cvss
